[
    {
        "imagen": "imagen",
        "nombre": "Tombow Dual Brush M",
        "precio": "$603.-"
    },
    {
        "imagen": "imagen",
        "nombre": "Tombow Dual Brush L",
        "precio": "603.-"
    },
    {
        "imagen": "imagen",
        "nombre": "Tombow Dual Brush A",
        "precio": "$603.-"
    },
    {
        "imagen": "imagen",
        "nombre": "Tombow Dual Brush N",
        "precio": "$603.-"
    },
    {
        "imagen": "imagen",
        "nombre": "Fudenosuke Tombow ",
        "precio": "$1870.-"
    },
    {
        "imagen": "imagen",
        "nombre": "Fudenosuke Tombow ",
        "precio": "$870.-"
    }
]